earthstat/__init__.py
earthstat/earthstat.py
earthstat/utils.py
earthstat/xearthstat.py
earthstat/analysis_aggregation/__init__.py
earthstat/analysis_aggregation/aggregate_process.py
earthstat/analysis_aggregation/parallel_clip_aggregate.py
earthstat/data_compatibility/__init__.py
earthstat/data_compatibility/compatibility_utils.py
earthstat/data_compatibility/data_compatibility.py
earthstat/data_compatibility/process_comp_issues.py
earthstat/data_converter/hdf5_to_tiff.py
earthstat/data_converter/netcdf_to_tiff.py
earthstat/geo_data_processing/__init__.py
earthstat/geo_data_processing/clip_raster.py
earthstat/geo_data_processing/rescale_resample_raster.py
earthstat/geo_data_processing/shapefile_process.py
earthstat/geo_meta_extractors/__init__.py
earthstat/geo_meta_extractors/mask_meta.py
earthstat/geo_meta_extractors/predictor_meta.py
earthstat/geo_meta_extractors/shapefile_meta.py
earthstat/xES/DailyDatasetBuilder.py
earthstat/xES/DekadalDatasetBuilder.py
earthstat/xES/__init__.py
earthstat/xES/cds_api_key_manager.py
earthstat/xES/cds_param.py
earthstat/xES/download_AgERA5py.py
earthstat/xES/get_csv.py
earthstat/xES/xES_utiles.py
earthstat-0.8.2.dist-info/LICENSE
earthstat-0.8.2.dist-info/METADATA
earthstat-0.8.2.dist-info/WHEEL
earthstat-0.8.2.dist-info/entry_points.txt
earthstat-0.8.2.dist-info/top_level.txt
earthstat-0.8.2.dist-info/RECORD
