Metadata-Version: 2.1
Name: earthstat
Version: 0.8.2
Summary: EarthStat Library
Author-email: Abdelrahman Saleh <abdulrahman.amr.ali@gmail.com>
License: MIT License
Project-URL: Homepage, https://github.com/AbdelrahmanAmr3/earthstat
Keywords: earthstat
Classifier: Intended Audience :: Developers
Classifier: License :: OSI Approved :: MIT License
Classifier: Natural Language :: English
Classifier: Programming Language :: Python :: 3.9
Classifier: Programming Language :: Python :: 3.10
Classifier: Programming Language :: Python :: 3.11
Classifier: Programming Language :: Python :: 3.12
Requires-Python: >=3.9
License-File: LICENSE
Requires-Dist: rasterio
Requires-Dist: shapely
Requires-Dist: numpy
Requires-Dist: pandas
Requires-Dist: tqdm
Requires-Dist: geopandas
Requires-Dist: pyproj
Requires-Dist: cdsapi
Requires-Dist: xarray ==2023.11.0
Requires-Dist: rioxarray
Provides-Extra: all
Requires-Dist: earthstat[extra] ; extra == 'all'
Provides-Extra: extra
Requires-Dist: pandas ; extra == 'extra'
Provides-Extra: gpu
Requires-Dist: cupy ; extra == 'gpu'
